{
  "$schema": "../../../../core/schemas/world.schema.json",
  "id": "01WLD_STABLE_149",
  "slug": "monde-nexus-149",
  "name": "Monde Nexus #149",
  "type": "STABLE_WORLD",
  "access_method": "STANDARD",
  "required_drift": 0.0,
  "description": "Un monde nexus d\u00e9couvert par l'\u00e9quipe Surface. Stable et accessible normalement.",
  "chronology": {
    "timescale": 1.1595608546849014,
    "drift": {
      "base": 0.014055253951219121,
      "variance": 0.013545669971702378
    },
    "decay_profile": "standard"
  },
  "pool": {
    "heroes_allowed": [
      "warriors",
      "visionaries",
      "mystics"
    ],
    "schools_allowed": [
      "geometry",
      "quantum",
      "speedforce"
    ]
  },
  "special_features": {
    "biome": "nexus",
    "resources": [
      "temporal_crystals",
      "void_essence"
    ],
    "unique_mechanic": "nexus_resonance"
  }
}