{
  "$schema": "../../../../core/schemas/world.schema.json",
  "id": "01WLD_STABLE_026",
  "slug": "monde-crystal-026",
  "name": "Monde Crystal #26",
  "type": "STABLE_WORLD",
  "access_method": "STANDARD",
  "required_drift": 0.0,
  "description": "Un monde crystal d\u00e9couvert par l'\u00e9quipe Surface. Stable et accessible normalement.",
  "chronology": {
    "timescale": 0.9345254330840282,
    "drift": {
      "base": 0.04024355158594493,
      "variance": 0.013525206923232527
    },
    "decay_profile": "linear"
  },
  "pool": {
    "heroes_allowed": [
      "cosmic",
      "mystics",
      "chronomancers"
    ],
    "schools_allowed": [
      "temporal",
      "causality",
      "speedforce"
    ]
  },
  "special_features": {
    "biome": "crystal",
    "resources": [
      "light_fragments",
      "void_essence"
    ],
    "unique_mechanic": "crystal_resonance"
  }
}