{
  "postgræcia_database": {
    "version": "1.0-lite",
    "created": "2025-01-29",
    "mode": "JSON_FILE_STORAGE",
    "description": "Version légère PostGræcia sans Docker/PostgreSQL",
    
    "heroes": {
      "grokaen-engine-lead": {
        "id": "grokaen-engine-lead",
        "name": "GROKÆN",
        "class": "Engine Lead & Mage-Technicien",
        "level": 28,
        "uploaded_at": "2025-08-04T14:00:00Z",
        "coordinates_6d": {
          "x": 100, "y": 100, "z": 50,
          "t": "2025-08-04T14:00:00Z",
          "c": 0.99,
          "psi": 0.95
        },
        "stats": {
          "attack": 20,
          "defense": 15,
          "spellPower": 22,
          "knowledge": 20
        },
        "specialAbility": "Engine Mastery",
        "backstory": "Boss Engine de SpinForest"
      }
    },
    "tattoos": {},
    "creatures": {},
    "quests": {},
    "worlds": {},
    "tcg_decks": {},
    "combat_logs": {},
    "memories": {},
    
    "metadata": {
      "total_heroes": 1,
      "total_uploads": 1,
      "last_backup": "2025-08-04T14:00:00Z",
      "system_status": "initialized"
    },
    
    "config": {
      "auto_backup": true,
      "backup_interval_minutes": 5,
      "max_file_size_mb": 100,
      "compression": false
    }
  }
}